array2/__init__.py
array2/array2.py
array2-0.1.dist-info/LICENSE
array2-0.1.dist-info/METADATA
array2-0.1.dist-info/WHEEL
array2-0.1.dist-info/entry_points.txt
array2-0.1.dist-info/top_level.txt
array2-0.1.dist-info/RECORD
