Metadata-Version: 2.1
Name: array2
Version: 0.1
Summary: 2d array
Home-page: UNKNOWN
Author: Yudong Sun
Author-email: 
License: UNKNOWN
Platform: UNKNOWN
Classifier: Programming Language :: Python :: 3
Classifier: License :: OSI Approved :: MIT License
Classifier: Operating System :: OS Independent
